domino/VERSION
domino/__init__.py
domino/base_piece.py
domino/logger.py
domino/task.py
domino/actions/github_actions.py
domino/cli/__init__.py
domino/cli/cli.py
domino/cli/utils/__init__.py
domino/cli/utils/config-domino-local.toml
domino/cli/utils/constants.py
domino/cli/utils/docker-compose.yaml
domino/cli/utils/pieces_repository.py
domino/cli/utils/platform.py
domino/client/__init__.py
domino/client/domino_backend_client.py
domino/client/github_rest_client.py
domino/client/local_files_client.py
domino/client/legacy/fs_client.py
domino/client/legacy/s3_client.py
domino/custom_operators/__init__.py
domino/custom_operators/docker_operator.py
domino/custom_operators/k8s_operator.py
domino/custom_operators/python_operator.py
domino/custom_operators/worker_operator.py
domino/custom_operators/deprecated/base_operator.py
domino/custom_operators/deprecated/external_python_operator.py
domino/custom_operators/sidecar/__init__.py
domino/custom_operators/sidecar/fuse.conf
domino/custom_operators/sidecar/logger.py
domino/custom_operators/sidecar/mount.py
domino/custom_operators/sidecar/rclone.conf
domino/custom_operators/sidecar/sidecar_lifecycle.sh
domino/exceptions/__init__.py
domino/exceptions/exceptions.py
domino/models/__init__.py
domino/models/output_modifier.py
domino/schemas/__init__.py
domino/schemas/container_resources.py
domino/schemas/deploy_mode.py
domino/schemas/display_result.py
domino/schemas/piece_metadata.py
domino/schemas/shared_storage.py
domino/scripts/__init__.py
domino/scripts/build_docker_images_pieces.py
domino/scripts/load_piece.py
domino/scripts/run_piece_docker.py
domino/scripts/deprecated/create_docker_compose_file.py
domino/scripts/deprecated/deprecated_piece_dry_run.py
domino/scripts/deprecated/docker_compose_constants.py
domino/scripts/deprecated/docker_compose_scripts.py
domino/scripts/deprecated/run_piece_bash.py
domino/storage/__init__.py
domino/storage/s3.py
domino/testing/__init__.py
domino/testing/dry_run.py
domino/testing/http_client.py
domino_py-0.9.4.dist-info/LICENSE
domino_py-0.9.4.dist-info/METADATA
domino_py-0.9.4.dist-info/WHEEL
domino_py-0.9.4.dist-info/entry_points.txt
domino_py-0.9.4.dist-info/top_level.txt
domino_py-0.9.4.dist-info/RECORD
