Metadata-Version: 2.1
Name: domino-py
Version: 0.9.4
Summary: Python package for Domino.
Author-email: Luiz Tauffer <luiz@taufferconsulting.com>, Vinicius Vaz <vinicius@taufferconsulting.com>
License: 
Project-URL: homepage, https://github.com/Tauffer-Consulting/domino
Project-URL: documentation, https://tauffer-consulting.github.io/domino-docs/
Project-URL: repository, https://github.com/Tauffer-Consulting/domino
Keywords: domino,airflow,gui
Classifier: Development Status :: 4 - Beta
Classifier: Programming Language :: Python :: 3
Classifier: Topic :: Scientific/Engineering
Classifier: Topic :: Software Development :: Libraries :: Python Modules
Classifier: Topic :: Software Development :: User Interfaces
Requires-Python: >=3.8
License-File: LICENSE
Requires-Dist: pydantic ==2.4.2
Requires-Dist: tomli ==2.0.1
Requires-Dist: tomli-w ==1.0.0
Requires-Dist: PyYAML ==6.0.1
Requires-Dist: jsonschema ==4.18.0
Requires-Dist: click ==8.1.3
Requires-Dist: rich >=13.4.2
Requires-Dist: colorama ==0.4.6
Provides-Extra: airflow
Requires-Dist: apache-airflow ==2.7.2 ; extra == 'airflow'
Requires-Dist: apache-airflow-providers-cncf-kubernetes ==5.0.0 ; extra == 'airflow'
Requires-Dist: apache-airflow-providers-docker ==3.6.0 ; extra == 'airflow'
Provides-Extra: cli
Requires-Dist: urllib3 ==1.26.15 ; extra == 'cli'
Requires-Dist: cryptography ==39.0.1 ; extra == 'cli'
Requires-Dist: pyOpenSSL ==23.1.1 ; extra == 'cli'
Requires-Dist: PyGithub ==1.55 ; extra == 'cli'
Requires-Dist: docker >=7.0.0 ; extra == 'cli'
Requires-Dist: kubernetes ==23.6.0 ; extra == 'cli'
Requires-Dist: bottle ==0.12.25 ; extra == 'cli'
Requires-Dist: requests ==2.31.0 ; extra == 'cli'
Provides-Extra: full
Requires-Dist: bottle ==0.12.25 ; extra == 'full'
Requires-Dist: urllib3 ==1.26.15 ; extra == 'full'
Requires-Dist: cryptography ==39.0.1 ; extra == 'full'
Requires-Dist: pyOpenSSL ==23.1.1 ; extra == 'full'
Requires-Dist: PyGithub ==1.55 ; extra == 'full'
Requires-Dist: docker >=6.0.1 ; extra == 'full'
Requires-Dist: kubernetes ==23.6.0 ; extra == 'full'
Requires-Dist: apache-airflow ==2.7.2 ; extra == 'full'
Requires-Dist: apache-airflow-providers-cncf-kubernetes ==5.0.0 ; extra == 'full'
Requires-Dist: apache-airflow-providers-docker ==3.6.0 ; extra == 'full'
